{
  "PROFILE": "PROFILE",
  "decrement": "decrement",
  "increment": "increment",
  "Аватар пользователя": "Аватар пользователя",
  "Введите текст комметария": "Введите текст комметария",
  "Возраст": "Возраст",
  "Войти": "Login",
  "Выйти": "",
  "Главная страница": "Главная страница",
  "Город": "Город",
  "Данные не указаны": "Данные не указаны",
  "Имя": "Имя",
  "Имя пользователя": "Username",
  "Кнопка": "",
  "Комментарии": "Комментарии",
  "Короткая версия": "",
  "Короткая весрия": "",
  "Назад к списку": "Назад к списку",
  "Не": "Не",
  "Некорректное имя или фамилия": "Некорректное имя или фамилия",
  "Некорректный Город": "Некорректный Город",
  "Некорректный возраст": "Некорректный возраст",
  "Неправильно введенеы логин или пароль": "",
  "Неправильно введены логин или пароль": "",
  "О сайте": "О сайте",
  "Отменить": "Отменить",
  "Отправить": "Отправить",
  "Пароль": "Password",
  "Перезагрузить страницу": "Перезагрузить страницу",
  "Попробуйте перезагрузить страницу": "Попробуйте перезагрузить страницу",
  "Произошла ошибка при загрузке профиля": "Произошла ошибка при загрузке профиля",
  "Профиль": "Профиль",
  "Редактировать": "Редактировать",
  "Серверная ошибка": "Серверная ошибка",
  "Сохранить": "Сохранить",
  "Список комментариев пуст": "Список комментариев пуст",
  "Статья не найдена": "Статья не найдена",
  "Страница не найдена": "Страница не найдена",
  "Укажите валюту": "",
  "Укажите страну": "",
  "Фамилия": "Фамилия",
  "Форма авторизации": "",
  "Читать далее": "Читать далее",
  "Что то пошло не так": "Что то пошло не так",
  "Язык": "Язык"
}
